sigwin_infra/__init__.py
sigwin_infra/resources/Certificates/common.mk
sigwin_infra/resources/Common/Platform/Darwin/default.mk
sigwin_infra/resources/Common/Platform/Linux/default.mk
sigwin_infra/resources/Common/Platform/Windows/default.mk
sigwin_infra/resources/Common/default/.editorconfig
sigwin_infra/resources/Common/default.mk
sigwin_infra/resources/Compose/common.mk
sigwin_infra/resources/Gitlab/compose.yaml
sigwin_infra/resources/Gitlab/docker-compose.yaml
sigwin_infra/resources/Gitlab/ssh.yaml
sigwin_infra/resources/Lighthouse/common.mk
sigwin_infra/resources/Monorepo/common.mk
sigwin_infra/resources/Node/application.mk
sigwin_infra/resources/Node/common.mk
sigwin_infra/resources/PHP/common/.editorconfig
sigwin_infra/resources/PHP/common/.gitattributes.dist
sigwin_infra/resources/PHP/common/.gitignore
sigwin_infra/resources/PHP/common/infection.json.dist
sigwin_infra/resources/PHP/common/phpstan.neon.dist
sigwin_infra/resources/PHP/common/phpunit.xml.dist
sigwin_infra/resources/PHP/common/psalm.xml.dist
sigwin_infra/resources/PHP/common.mk
sigwin_infra/resources/PHP/library/.php-cs-fixer.dist.php
sigwin_infra/resources/PHP/library/Makefile
sigwin_infra/resources/PHP/library.mk
sigwin_infra/resources/PHP/library_monorepo/Makefile
sigwin_infra/resources/PHP/library_monorepo.mk
sigwin_infra/resources/PHP/phar/box.json.dist
sigwin_infra/resources/PHP/phar.mk
sigwin_infra/resources/PHP/php-cs-fixer.php
sigwin_infra/resources/Pimcore/application/.editorconfig
sigwin_infra/resources/Pimcore/application/.gitignore
sigwin_infra/resources/Pimcore/application/Makefile
sigwin_infra/resources/Pimcore/application/phpstan.neon.dist
sigwin_infra/resources/Pimcore/application/psalm.xml.dist
sigwin_infra/resources/Pimcore/application.mk
sigwin_infra/resources/Pimcore/common.mk
sigwin_infra/resources/Pimcore/library/.gitattributes.dist
sigwin_infra/resources/Pimcore/library/.gitignore
sigwin_infra/resources/Pimcore/library/.php-cs-fixer.dist.php
sigwin_infra-1.23.3.dist-info/METADATA
sigwin_infra-1.23.3.dist-info/WHEEL
sigwin_infra-1.23.3.dist-info/RECORD
